flameshow/__init__.py
flameshow/colors.py
flameshow/const.py
flameshow/exceptions.py
flameshow/main.py
flameshow/models.py
flameshow/parsers/__init__.py
flameshow/parsers/stackcollapse_parser.py
flameshow/pprof_parser/__init__.py
flameshow/pprof_parser/parser.py
flameshow/pprof_parser/profile_pb2.py
flameshow/render/__init__.py
flameshow/render/app.py
flameshow/render/flamegraph.py
flameshow/render/framedetail.py
flameshow/render/header.py
flameshow/render/tabs.py
flameshow/runtime.py
flameshow/utils.py
flameshow-1.1.4.dist-info/METADATA
flameshow-1.1.4.dist-info/WHEEL
flameshow-1.1.4.dist-info/entry_points.txt
flameshow-1.1.4.dist-info/RECORD
