Metadata-Version: 2.3
Name: flameshow
Version: 1.1.4
Summary: A Terminal Flamegraph Viewer
License: GPLv3
Keywords: terminal,golang,pprof,flamegraph
Author: laixintao
Author-email: laixintaoo@gmail.com
Maintainer: laixintao
Maintainer-email: laixintaoo@gmail.com
Requires-Python: >=3.10,<4.0
Classifier: Development Status :: 5 - Production/Stable
Classifier: Environment :: Console
Classifier: Environment :: Console :: Curses
Classifier: Intended Audience :: Developers
Classifier: License :: Other/Proprietary License
Classifier: Operating System :: MacOS
Classifier: Operating System :: Microsoft :: Windows :: Windows 10
Classifier: Operating System :: Microsoft :: Windows :: Windows 11
Classifier: Operating System :: POSIX :: Linux
Classifier: Programming Language :: Python :: 3
Classifier: Programming Language :: Python :: 3.10
Classifier: Programming Language :: Python :: 3.11
Classifier: Programming Language :: Python :: 3.12
Classifier: Programming Language :: Python :: 3.13
Classifier: Typing :: Typed
Requires-Dist: click (>=8.1.7,<9.0.0)
Requires-Dist: iteround (>=1.0.4,<2.0.0)
Requires-Dist: protobuf (>=4.25,<5.0)
Requires-Dist: textual (>=0.37.1,<0.38.0)
Requires-Dist: typing-extensions (>=4.7.1,<5.0.0)
Project-URL: Bug Tracker, https://github.com/laixintao/flameshow/issues
Project-URL: Homepage, https://github.com/laixintao/flameshow
